JisuanjikexueDeJichuZhongwenban/README.md
JisuanjikexueDeJichuZhongwenban/__init__.py
JisuanjikexueDeJichuZhongwenban/__main__.py
JisuanjikexueDeJichuZhongwenban/file.epub
JisuanjikexueDeJichuZhongwenban/index.html
JisuanjikexueDeJichuZhongwenban/css/__init__.py
JisuanjikexueDeJichuZhongwenban/css/annotations.css
JisuanjikexueDeJichuZhongwenban/css/main.css
JisuanjikexueDeJichuZhongwenban/css/normalize.css
JisuanjikexueDeJichuZhongwenban/css/popup.css
JisuanjikexueDeJichuZhongwenban/font/__init__.py
JisuanjikexueDeJichuZhongwenban/font/fontello.eot
JisuanjikexueDeJichuZhongwenban/font/fontello.svg
JisuanjikexueDeJichuZhongwenban/font/fontello.ttf
JisuanjikexueDeJichuZhongwenban/font/fontello.woff
JisuanjikexueDeJichuZhongwenban/img/__init__.py
JisuanjikexueDeJichuZhongwenban/img/annotator-glyph-sprite.png
JisuanjikexueDeJichuZhongwenban/img/annotator-icon-sprite.png
JisuanjikexueDeJichuZhongwenban/img/apple-touch-icon.png
JisuanjikexueDeJichuZhongwenban/img/cancelfullscreen.png
JisuanjikexueDeJichuZhongwenban/img/close.png
JisuanjikexueDeJichuZhongwenban/img/fullscreen.png
JisuanjikexueDeJichuZhongwenban/img/loader.gif
JisuanjikexueDeJichuZhongwenban/img/menu-icon.png
JisuanjikexueDeJichuZhongwenban/img/save.png
JisuanjikexueDeJichuZhongwenban/img/saved.png
JisuanjikexueDeJichuZhongwenban/img/settings-s.png
JisuanjikexueDeJichuZhongwenban/img/settings.png
JisuanjikexueDeJichuZhongwenban/img/star.png
JisuanjikexueDeJichuZhongwenban/js/__init__.py
JisuanjikexueDeJichuZhongwenban/js/epub.js
JisuanjikexueDeJichuZhongwenban/js/epub.min.js
JisuanjikexueDeJichuZhongwenban/js/epub.min.map
JisuanjikexueDeJichuZhongwenban/js/hooks.min.js
JisuanjikexueDeJichuZhongwenban/js/hooks.min.map
JisuanjikexueDeJichuZhongwenban/js/reader.js
JisuanjikexueDeJichuZhongwenban/js/reader.js.map
JisuanjikexueDeJichuZhongwenban/js/reader.min.js
JisuanjikexueDeJichuZhongwenban/js/reader.min.map
JisuanjikexueDeJichuZhongwenban/js/hooks/__init__.py
jisuanjikexue_de_jichu_zhongwenban-2024.3.2.0.dist-info/METADATA
jisuanjikexue_de_jichu_zhongwenban-2024.3.2.0.dist-info/WHEEL
jisuanjikexue_de_jichu_zhongwenban-2024.3.2.0.dist-info/entry_points.txt
jisuanjikexue_de_jichu_zhongwenban-2024.3.2.0.dist-info/top_level.txt
jisuanjikexue_de_jichu_zhongwenban-2024.3.2.0.dist-info/RECORD
